docs/conf.py
jaxley/__init__.py
jaxley/__version__.py
jaxley/connect.py
jaxley/integrate.py
jaxley/solver_gate.py
jaxley/solver_voltage.py
jaxley/stimulus.py
jaxley/channels/__init__.py
jaxley/channels/channel.py
jaxley/channels/hh.py
jaxley/channels/pospischil.py
jaxley/channels/non_capacitive/__init__.py
jaxley/channels/non_capacitive/izhikevich.py
jaxley/channels/non_capacitive/rate.py
jaxley/channels/non_capacitive/spike.py
jaxley/io/__init__.py
jaxley/io/graph.py
jaxley/io/swc.py
jaxley/modules/__init__.py
jaxley/modules/base.py
jaxley/modules/branch.py
jaxley/modules/cell.py
jaxley/modules/compartment.py
jaxley/modules/network.py
jaxley/morphology/__init__.py
jaxley/morphology/distance_utils.py
jaxley/morphology/morph_utils.py
jaxley/optimize/__init__.py
jaxley/optimize/optimizer.py
jaxley/optimize/transforms.py
jaxley/optimize/utils.py
jaxley/pumps/__init__.py
jaxley/pumps/ca_pump.py
jaxley/pumps/faraday_electrolysis.py
jaxley/pumps/nernstreversal.py
jaxley/pumps/pump.py
jaxley/synapses/__init__.py
jaxley/synapses/ionotropic.py
jaxley/synapses/synapse.py
jaxley/synapses/tanh_conductance.py
jaxley/synapses/tanh_rate.py
jaxley/synapses/test.py
jaxley/utils/__init__.py
jaxley/utils/cell_utils.py
jaxley/utils/colors.py
jaxley/utils/debug_solver.py
jaxley/utils/dynamics.py
jaxley/utils/jax_utils.py
jaxley/utils/misc_utils.py
jaxley/utils/morph_attributes.py
jaxley/utils/plot_utils.py
jaxley/utils/solver_utils.py
jaxley/utils/syn_utils.py
jaxley-0.13.0.dist-info/licenses/LICENSE
tests/__init__.py
tests/conftest.py
tests/helpers.py
tests/test_api_equivalence.py
tests/test_cell_matches_branch.py
tests/test_channels.py
tests/test_clamp.py
tests/test_composability_of_modules.py
tests/test_connection.py
tests/test_data_feeding.py
tests/test_distance.py
tests/test_dynamics_utils.py
tests/test_fixtures.py
tests/test_grad.py
tests/test_graph.py
tests/test_groups.py
tests/test_ion_diffusion_and_pumps.py
tests/test_make_trainable.py
tests/test_misc.py
tests/test_moving.py
tests/test_optimize.py
jaxley-0.13.0.dist-info/METADATA
jaxley-0.13.0.dist-info/WHEEL
jaxley-0.13.0.dist-info/top_level.txt
jaxley-0.13.0.dist-info/RECORD
