Metadata-Version: 2.4
Name: Jaxley
Version: 0.13.0
Summary: Differentiable neuron simulations.
Author-email: jaxleyverse <jaxleyverse@gmail.com>
Keywords: neuroscience,biophysics,simulator,jax
Classifier: Intended Audience :: Developers
Classifier: Intended Audience :: Education
Classifier: Intended Audience :: Science/Research
Classifier: Topic :: Adaptive Technologies
Classifier: Topic :: Scientific/Engineering
Classifier: Topic :: Scientific/Engineering :: Mathematics
Classifier: License :: OSI Approved :: Apache Software License
Classifier: Natural Language :: English
Classifier: Operating System :: OS Independent
Classifier: Programming Language :: Python :: 3
Classifier: Development Status :: 3 - Alpha
Requires-Python: >=3.10
License-File: LICENSE
Requires-Dist: jax
Requires-Dist: matplotlib
Requires-Dist: numpy
Requires-Dist: pandas>=2.2.0
Requires-Dist: tridiax
Requires-Dist: networkx
Provides-Extra: doc
Requires-Dist: jupyter_contrib_nbextensions; extra == "doc"
Requires-Dist: notebook<=6.4.12; extra == "doc"
Requires-Dist: traitlets<=5.9.0; extra == "doc"
Requires-Dist: ipython<=8.9.0; extra == "doc"
Requires-Dist: mkdocs; extra == "doc"
Requires-Dist: mkdocs-material; extra == "doc"
Requires-Dist: markdown-include; extra == "doc"
Requires-Dist: mkdocs-redirects; extra == "doc"
Requires-Dist: mkdocstrings[python]>=0.18; extra == "doc"
Requires-Dist: mike; extra == "doc"
Requires-Dist: sphinx; extra == "doc"
Requires-Dist: sphinx-autobuild; extra == "doc"
Requires-Dist: sphinx_autodoc_typehints; extra == "doc"
Requires-Dist: sphinx-math-dollar; extra == "doc"
Requires-Dist: sphinx-design; extra == "doc"
Requires-Dist: myst-nb; extra == "doc"
Requires-Dist: jupytext; extra == "doc"
Requires-Dist: optax; extra == "doc"
Requires-Dist: sphinx-book-theme; extra == "doc"
Provides-Extra: dev
Requires-Dist: black; extra == "dev"
Requires-Dist: isort; extra == "dev"
Requires-Dist: jaxley-mech; extra == "dev"
Requires-Dist: neuron; extra == "dev"
Requires-Dist: pytest; extra == "dev"
Requires-Dist: pyright; extra == "dev"
Requires-Dist: optax; extra == "dev"
Requires-Dist: jupyter; extra == "dev"
Dynamic: license-file
